botweb/__init__.py
DiscordBotWeb-0.0.3.dist-info/LICENSE.txt
DiscordBotWeb-0.0.3.dist-info/METADATA
DiscordBotWeb-0.0.3.dist-info/WHEEL
DiscordBotWeb-0.0.3.dist-info/top_level.txt
DiscordBotWeb-0.0.3.dist-info/RECORD
