Metadata-Version: 2.1
Name: DiscordBotWeb
Version: 0.0.3
Summary: Make A Simple Website For Your Discord Bot Without Any HTML Knowledge!
Home-page: UNKNOWN
Author: nooby xviii
Author-email: xviii2008@gmail.com
License: UNKNOWN
Platform: UNKNOWN
Classifier: Programming Language :: Python :: 3
Classifier: License :: OSI Approved :: MIT License
Classifier: Operating System :: OS Independent
Requires-Python: >=3.6
